{
  "id": "europe-interdit-visuels-ia",
  "titre": "Le Parlement européen ferme la porte aux visuels IA",
  "categorie": "tech",
  "auteur": "Shams & Dean",
  "date": "3 avril 2026",
  "resume": "Commission, Conseil, Parlement : les trois institutions européennes s'alignent pour bannir les visuels entièrement générés par IA de leur communication officielle. Un choix qui tranche avec ce qui se pratique ailleurs.",
  "contenu": "Fin mars 2026, les trois grandes institutions de l'Union européenne ont posé une règle commune : fini les images ou vidéos fabriquées de toutes pièces par une IA dans leur communication officielle. Commission, Conseil, Parlement parlent d'une seule voix. C'est rare. Et ça mérite qu'on s'y arrête.\n\nThomas Regnier, porte-parole de la Commission européenne, l'a formulé clairement à Politico : les visuels mis à disposition des journalistes ou utilisés à des fins d'information officielle n'incluent pas de contenus générés par IA. La nuance est importante. Améliorer une image réelle reste autorisé. En inventer une nouvelle de zéro, jamais.\n\n## Grok a accéléré la prise de conscience\n\nCette décision ne tombe pas du ciel. Elle s'inscrit dans un contexte précis. Depuis fin 2025, l'IA d'Elon Musk a produit des images sexualisées non consenties mettant en scène des personnalités publiques, dont Taylor Swift, ainsi que des mineurs. Le 26 mars 2026, 569 eurodéputés sur 614 ont adopté un amendement à l'AI Act pour encadrer ces dérives. Le vote n'a pas été symbolique. Il a été massif.\n\nÀ mi-mars, les institutions ont publié leurs directives internes. En France, au Royaume-Uni, à Bruxelles, les enquêtes contre Grok s'enchaînent. La complaisance n'est plus une option.\n\n## Le contraste avec ce qui se passe ailleurs\n\nSoyons directs : le choix européen n'est pas universel. Loin de là.\n\nDepuis son investiture, Donald Trump a utilisé des contenus générés par IA dans 36 publications sur Truth Social, selon le Poynter Institute. Parmi eux, une image le représentant en pape, une vidéo le montrant déverser des ordures sur des manifestants. En Hongrie, des deepfakes du Premier ministre ont été produits pour attaquer Bruxelles. En Allemagne, le chancelier a utilisé l'IA pour vulgariser l'intelligence artificielle dans sa communication.\n\nL'Union européenne choisit donc de faire de sa propre communication un terrain de séparation nette. Ce n'est pas de la prudence excessive. C'est un positionnement politique.\n\n## Ce que dit le cadre légal\n\nL'AI Act pose des interdictions claires. L'article 5 prohibe la biométrie forcée et les manipulations subliminales. Le bouclier démocratique contraint les plateformes face aux ingérences étrangères. Le 17 mars 2026, un report partiel des règles a été voté, mais le cap reste le même.\n\nLes abus privés continueront. Personne ne le nie. Mais les standards publics bougent. Et quand les institutions donnent le ton, les gouvernements nationaux finissent par suivre ou par s'expliquer.\n\n## La question que chaque citoyen peut poser\n\nCette décision européenne ouvre une pratique simple. Chaque fois qu'un élu ou une institution publie un visuel, la question devient légitime : cette image vient d'où ? A-t-elle été générée par IA ?\n\nPoser cette question, c'est exercer une pression réelle. La réponse imposera la transparence ou révélera ce qu'on préférerait taire. Dans un monde où le vrai et le faux se ressemblent de plus en plus, c'est peut-être le geste le plus concret que chacun puisse faire.\n\n> **Sources :**\n> KultureGeek, _L'Union européenne interdit les images et vidéos IA dans sa communication_, 1er avril 2026 · https://kulturegeek.fr/news-350049/lunion-europeenne-interdit-images-videos-ia-communication\n> Le Monde, _Le Parlement européen interdit les images pornographiques générées par IA_, 26 mars 2026 · https://www.lemonde.fr/international/article/2026/03/26/le-parlement-europeen-interdit-les-images-pornographiques-generees-par-ia\n> Le Figaro, _Des eurodéputés veulent interdire la création par IA de deepfakes sexuels_, 18 mars 2026 · https://www.lefigaro.fr/secteur/high-tech/des-eurodeputes-veulent-interdire-la-creation-par-ia-de-deepfakes-sexuels-20260318\n> Entreprises.gouv.fr, _Le règlement européen sur l'intelligence artificielle_ · https://www.entreprises.gouv.fr/decryptages-de-nos-experts/le-reglement-europeen-sur-lintelligence-artificielle-publics-concerne\n> 01net, _Désinformation et deepfake : l'UE présente son bouclier démocratique_ · https://www.01net.com/actualites/desinformation-deepfake-lue-presente-son-bouclier-democratique-contre-lingerence-etrangere.html\n> Europarl.europa.eu, _Les députés soutiennent le report de certaines règles sur l'IA_, 17 mars 2026 · https://www.europarl.europa.eu/news/fr/press-room/20260316IPR38219/les-deputes-soutiennent-le-report-de-certaines-regles-sur-l-ia"
}
